AUTHORS.rst
CONTRIBUTING.rst
HISTORY.rst
LICENSE
MANIFEST.in
README.rst
setup.cfg
setup.py
docs/Makefile
docs/authors.rst
docs/conf.py
docs/contributing.rst
docs/history.rst
docs/index.rst
docs/installation.rst
docs/make.bat
docs/readme.rst
docs/usage.rst
gumazon/__init__.py
gumazon/cli.py
gumazon/gumazon.py
gumazon.egg-info/PKG-INFO
gumazon.egg-info/SOURCES.txt
gumazon.egg-info/dependency_links.txt
gumazon.egg-info/entry_points.txt
gumazon.egg-info/not-zip-safe
gumazon.egg-info/top_level.txt
tests/__init__.py
tests/test_gumazon.py