Metadata-Version: 2.1
Name: gumazon
Version: 0.1.0
Summary: Gumazon Application
Home-page: https://github.com/gumshoe00/gumazon
Author: Gumshoe Media Inc.
Author-email: admin@gumazon.io
License: GNU General Public License v3
Keywords: gumazon
Platform: UNKNOWN
Classifier: Development Status :: 2 - Pre-Alpha
Classifier: Intended Audience :: Developers
Classifier: License :: OSI Approved :: GNU General Public License v3 (GPLv3)
Classifier: Natural Language :: English
Classifier: Programming Language :: Python :: 3
Classifier: Programming Language :: Python :: 3.6
Classifier: Programming Language :: Python :: 3.7
Classifier: Programming Language :: Python :: 3.8
Requires-Python: >=3.6
License-File: LICENSE
License-File: AUTHORS.rst
